wikipeople/__init__.py
wikipeople/wikipeople.py
wikipeople-0.4.dist-info/METADATA
wikipeople-0.4.dist-info/WHEEL
wikipeople-0.4.dist-info/top_level.txt
wikipeople-0.4.dist-info/RECORD
